{
  "type": "forge:conditional",
  "recipes": [
    {
      "conditions": [
        {
          "value": {
            "tag": "forge:ingots/zinc",
            "type": "forge:tag_empty"
          },
          "type": "forge:not"
        }
      ],
      "recipe": {
        "type": "grindr:blasting",
        "ingredient": {
          "item": "grindr:zinc_dust"
        },
        "result": {
          "tag": "forge:ingots/zinc"
        },
        "experience": 0.125,
        "cookingtime": 100
      }
    }
  ]
}